stylebase/__init__.py
stylebase/__main__.py
stylebase/test.py
tests/__init__.py
tests/__main__.py
stylebase-0.0.47.dist-info/LICENSE
stylebase-0.0.47.dist-info/METADATA
stylebase-0.0.47.dist-info/WHEEL
stylebase-0.0.47.dist-info/entry_points.txt
stylebase-0.0.47.dist-info/top_level.txt
stylebase-0.0.47.dist-info/RECORD
