Metadata-Version: 2.1
Name: stylebase
Version: 0.0.47
Summary: Create a style for your Python desktop app
Home-page: https://github.com/pyrustic/stylebase
Author: Pyrustic Evangelist
Author-email: pyrustic@protonmail.com
Maintainer: Pyrustic Evangelist
Maintainer-email: pyrustic@protonmail.com
License: MIT
Keywords: library,styling,style,gui,tkinter,desktop-app
Platform: UNKNOWN
Classifier: Programming Language :: Python :: 3
Classifier: License :: OSI Approved :: MIT License
Classifier: Operating System :: OS Independent
Requires-Python: >=3.5
License-File: LICENSE
